LICENSE
README.md
setup.py
src/haimgard/haimgard.py
src/haimgard.egg-info/PKG-INFO
src/haimgard.egg-info/SOURCES.txt
src/haimgard.egg-info/dependency_links.txt
src/haimgard.egg-info/entry_points.txt
src/haimgard.egg-info/not-zip-safe
src/haimgard.egg-info/requires.txt
src/haimgard.egg-info/top_level.txt
src/haimgard/modules/dos/icmp.py
src/haimgard/modules/dos/slowloris.py
src/haimgard/modules/dos/tcp.py
src/haimgard/modules/dos/udp.py
src/haimgard/modules/scan/commonports.py
src/haimgard/modules/scan/macdedection.py
src/haimgard/modules/scan/network.py
src/haimgard/modules/scan/osdedection.py
src/haimgard/modules/scan/port.py
src/haimgard/modules/scan/scriptauth.py
src/haimgard/modules/scan/scriptbroadcast.py
src/haimgard/modules/scan/scriptbrute.py
src/haimgard/modules/scan/scriptdefault.py
src/haimgard/modules/scan/scriptdiscovery.py
src/haimgard/modules/scan/scriptdos.py
src/haimgard/modules/scan/scriptexploit.py
src/haimgard/modules/scan/scriptexternal.py
src/haimgard/modules/scan/scriptfuzzer.py
src/haimgard/modules/scan/scriptmalware.py
src/haimgard/modules/scan/scriptversion.py
src/haimgard/modules/scan/scriptvuln.py
src/haimgard/modules/scan/servicededection.py
src/haimgard/modules/scan/wafdedection.py
src/haimgard/modules/scan/webservicededection.py
src/haimgard/modules/scan/whois.py
src/haimgard/modules/wordpress/adminpagededection.py
src/haimgard/modules/wordpress/crondedection.py
src/haimgard/modules/wordpress/feeddedection.py
src/haimgard/modules/wordpress/forgottenpassdedection.py
src/haimgard/modules/wordpress/includesdedection.py
src/haimgard/modules/wordpress/loginpagededection.py
src/haimgard/modules/wordpress/plugins.txt
src/haimgard/modules/wordpress/pluginsdedection.py
src/haimgard/modules/wordpress/pluginspagededection.py
src/haimgard/modules/wordpress/readmededection.py
src/haimgard/modules/wordpress/themes.txt
src/haimgard/modules/wordpress/themesdedection.py
src/haimgard/modules/wordpress/themespagededection.py
src/haimgard/modules/wordpress/uploadsdedection.py
src/haimgard/modules/wordpress/userdedection.py
src/haimgard/modules/wordpress/versiondedection.py
src/haimgard/modules/wordpress/wafdedection.py
src/haimgard/modules/wordpress/xmlrpcdedection.py