Metadata-Version: 2.1
Name: haimgard
Version: 0.10.0
Summary: Haimgard is an environment for writing, testing and using exploit code.
Home-page: https://github.com/onuratakan/Haimgard
Author: Onur Atakan ULUSOY - PwnWiki
Author-email: atadogan06@gmail.com
License: MIT
Platform: UNKNOWN
Requires-Python: >=3.6
License-File: LICENSE
